MANIFEST.in
README.rst
requirements.txt
setup.py
pytimetrack/__init__.py
pytimetrack.egg-info/PKG-INFO
pytimetrack.egg-info/SOURCES.txt
pytimetrack.egg-info/dependency_links.txt
pytimetrack.egg-info/requires.txt
pytimetrack.egg-info/top_level.txt
pytimetrack/core/__init__.py
pytimetrack/core/calc.py
pytimetrack/core/model.py
pytimetrack/core/track.py
pytimetrack/dataframe/__init__.py
pytimetrack/dataframe/model.py
pytimetrack/dataframe/track.py
pytimetrack/wrapper/__init__.py
pytimetrack/wrapper/pandas.py